[
 {
  "results": {
   "packetdrill_dss": {
    "13": {
     "result": "flaky",
     "name": "packetdrill: mptcp/dss/dss_fin_rcv_retrans_fin.pkt (ipv4)",
     "comment": "IGNORE Flaky"
    }
   }
  },
  "run_id": "27868011058",
  "tag": "20260620--121152"
 },
 {
  "results": {
   "packetdrill_dss": {
    "43": {
     "result": "flaky",
     "name": "packetdrill: mptcp/dss/mpc_with_data_server_window_close.pkt (ipv4)",
     "comment": "IGNORE Flaky"
    },
    "44": {
     "result": "flaky",
     "name": "packetdrill: mptcp/dss/mpc_with_data_server_window_close.pkt (ipv4-mapped-v6)",
     "comment": "IGNORE Flaky"
    }
   },
   "packetdrill_mp_capable": {
    "23": {
     "result": "flaky",
     "name": "packetdrill: mptcp/mp_capable/v1_connect_tcpfallback_flagB.pkt (ipv4-mapped-v6)",
     "comment": "IGNORE Flaky"
    },
    "28": {
     "result": "flaky",
     "name": "packetdrill: mptcp/mp_capable/v1_connect_tcpfallback_no_mpc_close_data.pkt (ipv4)",
     "comment": "IGNORE Flaky"
    },
    "30": {
     "result": "flaky",
     "name": "packetdrill: mptcp/mp_capable/v1_connect_tcpfallback_no_mpc_close_data.pkt (ipv6)",
     "comment": "IGNORE Flaky"
    }
   },
   "packetdrill_sockopts": {
    "4": {
     "result": "flaky",
     "name": "packetdrill: mptcp/sockopts/sockopt_TCP_NOTSENT_LOWAT.pkt (ipv4)",
     "comment": "IGNORE Flaky"
    },
    "6": {
     "result": "flaky",
     "name": "packetdrill: mptcp/sockopts/sockopt_TCP_NOTSENT_LOWAT.pkt (ipv6)",
     "comment": "IGNORE Flaky"
    }
   }
  },
  "run_id": "28020266040",
  "tag": "20260623--121727"
 },
 {
  "results": {
   "packetdrill_mp_capable": {
    "23": {
     "result": "flaky",
     "name": "packetdrill: mptcp/mp_capable/v1_connect_tcpfallback_flagB.pkt (ipv4-mapped-v6)",
     "comment": "IGNORE Flaky"
    },
    "28": {
     "result": "flaky",
     "name": "packetdrill: mptcp/mp_capable/v1_connect_tcpfallback_no_mpc_close_data.pkt (ipv4)",
     "comment": "IGNORE Flaky"
    },
    "24": {
     "result": "flaky",
     "name": "packetdrill: mptcp/mp_capable/v1_connect_tcpfallback_flagB.pkt (ipv6)",
     "comment": "IGNORE Flaky"
    },
    "31": {
     "result": "flaky",
     "name": "packetdrill: mptcp/mp_capable/v1_connect_tcpfallback_wrongver.pkt (ipv4)",
     "comment": "IGNORE Flaky"
    },
    "26": {
     "result": "flaky",
     "name": "packetdrill: mptcp/mp_capable/v1_connect_tcpfallback_flagH.pkt (ipv4-mapped-v6)",
     "comment": "IGNORE Flaky"
    }
   }
  },
  "run_id": "28091992658",
  "tag": "20260624--115901"
 },
 {
  "results": {
   "packetdrill_dss": {
    "23": {
     "result": "flaky",
     "name": "packetdrill: mptcp/dss/dss_fin_retrans_last_ack.pkt (ipv4-mapped-v6)",
     "comment": "IGNORE Flaky"
    },
    "46": {
     "result": "flaky",
     "name": "packetdrill: mptcp/dss/mptcp_eor_no_coalesce.pkt (ipv4)",
     "comment": "IGNORE Flaky"
    }
   },
   "packetdrill_sockopts": {
    "7": {
     "result": "flaky",
     "name": "packetdrill: mptcp/sockopts/sockopt_cork_nodelay.pkt (ipv4)",
     "comment": "IGNORE Flaky"
    }
   }
  },
  "run_id": "28163238721",
  "tag": "20260625--121236"
 },
 {
  "results": {
   "packetdrill_dss": {
    "46": {
     "result": "flaky",
     "name": "packetdrill: mptcp/dss/mptcp_eor_no_coalesce.pkt (ipv4)",
     "comment": "IGNORE Flaky"
    }
   },
   "packetdrill_mp_capable": {
    "28": {
     "result": "flaky",
     "name": "packetdrill: mptcp/mp_capable/v1_connect_tcpfallback_no_mpc_close_data.pkt (ipv4)",
     "comment": "IGNORE Flaky"
    }
   }
  },
  "run_id": "28232282704",
  "tag": "20260626--120954"
 },
 {
  "results": {},
  "run_id": "28285292766",
  "tag": "20260627--115426"
 },
 {
  "results": {
   "packetdrill_dss": {
    "12": {
     "result": "flaky",
     "name": "packetdrill: mptcp/dss/dss_fin_rcv_data_no_mpc.pkt (ipv6)",
     "comment": "IGNORE Flaky"
    }
   },
   "packetdrill_syscalls": {
    "13": {
     "result": "flaky",
     "name": "packetdrill: mptcp/syscalls/connect_close_full.pkt (ipv4)",
     "comment": "IGNORE Flaky"
    }
   }
  },
  "run_id": "28370659972",
  "tag": "20260629--134142"
 },
 {
  "results": {
   "packetdrill_dss": {
    "24": {
     "result": "flaky",
     "name": "packetdrill: mptcp/dss/dss_fin_retrans_last_ack.pkt (ipv6)",
     "comment": "IGNORE Flaky"
    }
   },
   "packetdrill_mp_capable": {
    "2": {
     "result": "flaky",
     "name": "packetdrill: mptcp/mp_capable/v1_bind_tcpfallback_flagB.pkt (ipv4-mapped-v6)",
     "comment": "IGNORE Flaky"
    },
    "10": {
     "result": "flaky",
     "name": "packetdrill: mptcp/mp_capable/v1_bind_tcpfallback_flagH_3rd_ack.pkt (ipv4)",
     "comment": "IGNORE Flaky"
    }
   }
  },
  "run_id": "28438031247",
  "tag": "20260630--121043"
 },
 {
  "results": {
   "packetdrill_regressions": {
    "5": {
     "result": "flaky",
     "name": "packetdrill: mptcp/regressions/close_mpj_timeout_wakeup.pkt (ipv4-mapped-v6)",
     "comment": "IGNORE Flaky"
    }
   },
   "selftest_mptcp_join_subtests": {
    "121": {
     "result": "flaky",
     "name": "mptcp_join: Infinite map",
     "comment": "IGNORE Flaky",
     "time_ms": "41874"
    }
   }
  },
  "run_id": "28511959997",
  "tag": "20260701--121901"
 },
 {
  "results": {
   "packetdrill_dss": {
    "12": {
     "result": "flaky",
     "name": "packetdrill: mptcp/dss/dss_fin_rcv_data_no_mpc.pkt (ipv6)",
     "comment": "IGNORE Flaky"
    }
   }
  },
  "run_id": "28735731354",
  "tag": "20260705--104903"
 },
 {
  "results": {
   "packetdrill_dss": {
    "12": {
     "result": "flaky",
     "name": "packetdrill: mptcp/dss/dss_fin_rcv_data_no_mpc.pkt (ipv6)",
     "comment": "IGNORE Flaky"
    },
    "10": {
     "result": "flaky",
     "name": "packetdrill: mptcp/dss/dss_fin_rcv_data_no_mpc.pkt (ipv4)",
     "comment": "IGNORE Flaky"
    },
    "15": {
     "result": "flaky",
     "name": "packetdrill: mptcp/dss/dss_fin_rcv_retrans_fin.pkt (ipv6)",
     "comment": "IGNORE Flaky"
    }
   }
  },
  "run_id": "28859467033",
  "tag": "20260707--120754"
 },
 {
  "results": {
   "packetdrill_mp_capable": {
    "1": {
     "result": "flaky",
     "name": "packetdrill: mptcp/mp_capable/v1_bind_tcpfallback_flagB.pkt (ipv4)",
     "comment": "IGNORE Flaky"
    },
    "3": {
     "result": "flaky",
     "name": "packetdrill: mptcp/mp_capable/v1_bind_tcpfallback_flagB.pkt (ipv6)",
     "comment": "IGNORE Flaky"
    },
    "25": {
     "result": "flaky",
     "name": "packetdrill: mptcp/mp_capable/v1_connect_tcpfallback_flagH.pkt (ipv4)",
     "comment": "IGNORE Flaky"
    },
    "32": {
     "result": "flaky",
     "name": "packetdrill: mptcp/mp_capable/v1_connect_tcpfallback_wrongver.pkt (ipv4-mapped-v6)",
     "comment": "IGNORE Flaky"
    }
   }
  },
  "run_id": "28932381993",
  "tag": "20260708--110557"
 },
 {
  "results": {
   "packetdrill_dss": {
    "4": {
     "result": "flaky",
     "name": "packetdrill: mptcp/dss/dss_drop_after_data_fallback_server.pkt (ipv4)",
     "comment": "IGNORE Flaky"
    },
    "6": {
     "result": "flaky",
     "name": "packetdrill: mptcp/dss/dss_drop_after_data_fallback_server.pkt (ipv6)",
     "comment": "IGNORE Flaky"
    },
    "5": {
     "result": "flaky",
     "name": "packetdrill: mptcp/dss/dss_drop_after_data_fallback_server.pkt (ipv4-mapped-v6)",
     "comment": "IGNORE Flaky"
    }
   },
   "packetdrill_mp_capable": {
    "1": {
     "result": "flaky",
     "name": "packetdrill: mptcp/mp_capable/v1_bind_tcpfallback_flagB.pkt (ipv4)",
     "comment": "IGNORE Flaky"
    }
   }
  },
  "run_id": "29011729929",
  "tag": "20260709--120601"
 }
]
